my_decimal.py
my_decimal-0.1.1.dist-info/LICENSE
my_decimal-0.1.1.dist-info/METADATA
my_decimal-0.1.1.dist-info/WHEEL
my_decimal-0.1.1.dist-info/top_level.txt
my_decimal-0.1.1.dist-info/RECORD
